{
	"schema_version": 1,
	"quilt_loader": {
		"group": "gay.lemmaeof",
		"id": "kdlycontent",
		"version": "${version}",
		"metadata": {
			"name": "Kdly Content",
			"description": "A system for writing simple blocks and items in kdl",
			"contributors": {
				"LemmaEOF": "Owner"
			},
			"contact": {
				"homepage": "https://lemmaeof.gay/",
				"issues": "https://github.com/LemmaEOF/KdlyContent/issues",
				"sources": "https://github.com/LemmaEOF/KdlyContent"
			},
			"icon": "assets/kdlycontent/icon.png"
		},
		"intermediate_mappings": "net.fabricmc:intermediary",
		"entrypoints": {
			"init": "gay.lemmaeof.kdlycontent.KdlyContent",
			"client_init": "gay.lemmaeof.kdlycontent.client.KdlyContentClient"
		},
		"depends": [
			{
				"id": "quilt_loader",
				"versions": ">=0.17.0-"
			},
			{
				"id": "quilted_fabric_api",
				"versions": ">=1.0.0-"
			},
			{
				"id": "minecraft",
				"versions": ">=1.18"
			}
		]
	}
}
